edgework/NHL API Documentation.md
edgework/__init__.py
edgework/const.py
edgework/edgework.py
edgework/endpoints.py
edgework/errors.py
edgework/http_client.py
edgework/utilities.py
edgework/.cache/teams.json
edgework/clients/__init__.py
edgework/clients/game_client.py
edgework/clients/glossary_client.py
edgework/clients/player_client.py
edgework/clients/schedule_client.py
edgework/clients/shift_client.py
edgework/clients/standings_client.py
edgework/clients/stats_client.py
edgework/clients/team_client.py
edgework/models/__init__.py
edgework/models/base.py
edgework/models/config.py
edgework/models/draft.py
edgework/models/game.py
edgework/models/game_events.py
edgework/models/glossary.py
edgework/models/player.py
edgework/models/playoffs.py
edgework/models/schedule.py
edgework/models/shift.py
edgework/models/standings.py
edgework/models/stats.py
edgework/models/team.py
edgework-0.5.1.dist-info/licenses/LICENSE
edgework-0.5.1.dist-info/METADATA
edgework-0.5.1.dist-info/WHEEL
edgework-0.5.1.dist-info/top_level.txt
edgework-0.5.1.dist-info/RECORD
