Metadata-Version: 2.4
Name: edgework
Version: 0.5.1
Author-email: problemxl <email@email.com>
Requires-Python: <4.0,>=3.11
License-File: LICENSE
Requires-Dist: aiohttp<4.0.0,>=3.9.1
Requires-Dist: loguru<1.0.0,>=0.7.2
Requires-Dist: httpx<1.0.0,>=0.27.0
Requires-Dist: pydantic>=2.10.6
Requires-Dist: black>=25.1.0
Requires-Dist: isort>=6.0.1
Dynamic: license-file
